humint/__init__.py
humint/cli.py
humint/humint.py
humint-0.1.0.dist-info/LICENSE
humint-0.1.0.dist-info/METADATA
humint-0.1.0.dist-info/WHEEL
humint-0.1.0.dist-info/entry_points.txt
humint-0.1.0.dist-info/RECORD
